{
    "@context": "http://iiif.io/api/presentation/2/context.json",
    "@id": "https://raw.githubusercontent.com/nakamura196/omekac_uparl/master/docs/oa/items/209/annolist.json",
    "@type": "sc:AnnotationList",
    "resources": [
        {
            "@context": "http://iiif.io/api/presentation/2/context.json",
            "@id": "https://diyhistory.org/uparl/omeka/oa/items/14704/anno.json",
            "@type": "oa:Annotation",
            "motivation": "oa:commenting",
            "on": [
                {
                    "@type": "oa:SpecificResource",
                    "full": "https://iiif.dl.itc.u-tokyo.ac.jp/repo/iiif/167779/canvas/p13",
                    "selector": {
                        "@type": "oa:Choice",
                        "default": {
                            "@type": "oa:FragmentSelector",
                            "value": "xywh=5861,840,1340,4829"
                        },
                        "item": {
                            "@type": "oa:SvgSelector",
                            "value": "<svg xmlns='http://www.w3.org/2000/svg'><path xmlns=\"http://www.w3.org/2000/svg\" d=\"M5861.24709,839.58744h670.01825v0h670.01825v2414.46771v2414.46771h-670.01825h-670.01825v-2414.46771z\" data-paper-data=\"{&quot;strokeWidth&quot;:1,&quot;rotation&quot;:0,&quot;deleteIcon&quot;:null,&quot;rotationIcon&quot;:null,&quot;group&quot;:null,&quot;editable&quot;:true,&quot;annotation&quot;:null}\" id=\"rectangle_a8fbda7d-cd15-4776-9346-baff6dd8be29\" fill-opacity=\"0\" fill=\"#00bfff\" fill-rule=\"nonzero\" stroke=\"#00bfff\" stroke-width=\"1\" stroke-linecap=\"butt\" stroke-linejoin=\"miter\" stroke-miterlimit=\"10\" stroke-dasharray=\"\" stroke-dashoffset=\"0\" font-family=\"none\" font-weight=\"none\" font-size=\"none\" text-anchor=\"none\" style=\"mix-blend-mode: normal\"/></svg>"
                        }
                    },
                    "within": {
                        "@id": "https://raw.githubusercontent.com/nakamura196/omekac_uparl/master/docs/oa/items/209/manifest.json",
                        "@type": "sc:Manifest"
                    }
                }
            ],
            "resource": [
                {
                    "@type": "dctypes:Text",
                    "chars": "<p><span style=\"font-size: 10pt; font-family: Arial;\" data-sheets-value=\"{&quot;1&quot;:2,&quot;2&quot;:&quot;星鳳樓帖-04-15&quot;}\" data-sheets-userformat=\"{&quot;2&quot;:513,&quot;3&quot;:[null,0],&quot;12&quot;:0}\">星鳳樓帖-04-15@東京大学</span></p>",
                    "format": "text/html"
                }
            ]
        },
        {
            "@context": "http://iiif.io/api/presentation/2/context.json",
            "@id": "https://diyhistory.org/uparl/omeka/oa/items/14705/anno.json",
            "@type": "oa:Annotation",
            "motivation": "oa:commenting",
            "on": [
                {
                    "@type": "oa:SpecificResource",
                    "full": "https://iiif.dl.itc.u-tokyo.ac.jp/repo/iiif/167779/canvas/p13",
                    "selector": {
                        "@type": "oa:Choice",
                        "default": {
                            "@type": "oa:FragmentSelector",
                            "value": "xywh=4423,840,1428,4804"
                        },
                        "item": {
                            "@type": "oa:SvgSelector",
                            "value": "<svg xmlns='http://www.w3.org/2000/svg'><path xmlns=\"http://www.w3.org/2000/svg\" d=\"M4423.17048,839.58744h713.7858v0h713.7858v2401.9627v2401.9627h-713.7858h-713.7858v-2401.9627z\" data-paper-data=\"{&quot;strokeWidth&quot;:1,&quot;rotation&quot;:0,&quot;deleteIcon&quot;:null,&quot;rotationIcon&quot;:null,&quot;group&quot;:null,&quot;editable&quot;:true,&quot;annotation&quot;:null}\" id=\"rectangle_81c59852-a3eb-4569-872a-0ba167ecff09\" fill-opacity=\"0\" fill=\"#00bfff\" fill-rule=\"nonzero\" stroke=\"#00bfff\" stroke-width=\"1\" stroke-linecap=\"butt\" stroke-linejoin=\"miter\" stroke-miterlimit=\"10\" stroke-dasharray=\"\" stroke-dashoffset=\"0\" font-family=\"none\" font-weight=\"none\" font-size=\"none\" text-anchor=\"none\" style=\"mix-blend-mode: normal\"/></svg>"
                        }
                    },
                    "within": {
                        "@id": "https://diyhistory.org/uparl/omeka/oa/items/209/manifest.json",
                        "@type": "sc:Manifest"
                    }
                }
            ],
            "resource": [
                {
                    "@type": "dctypes:Text",
                    "chars": "<p><span style=\"font-size: 10pt; font-family: Arial;\" data-sheets-value=\"{&quot;1&quot;:2,&quot;2&quot;:&quot;星鳳樓帖-04-26&quot;}\" data-sheets-userformat=\"{&quot;2&quot;:513,&quot;3&quot;:[null,0],&quot;12&quot;:0}\">星鳳樓帖-04-26@東京大学</span></p>",
                    "format": "text/html"
                }
            ]
        },
        {
            "@context": "http://iiif.io/api/presentation/2/context.json",
            "@id": "https://diyhistory.org/uparl/omeka/oa/items/14706/anno.json",
            "@type": "oa:Annotation",
            "motivation": "oa:commenting",
            "on": [
                {
                    "@type": "oa:SpecificResource",
                    "full": "https://iiif.dl.itc.u-tokyo.ac.jp/repo/iiif/167779/canvas/p13",
                    "selector": {
                        "@type": "oa:Choice",
                        "default": {
                            "@type": "oa:FragmentSelector",
                            "value": "xywh=2272,852,1715,4779"
                        },
                        "item": {
                            "@type": "oa:SvgSelector",
                            "value": "<svg xmlns='http://www.w3.org/2000/svg'><path xmlns=\"http://www.w3.org/2000/svg\" d=\"M2272.30806,852.09246h857.59346v0h857.59346v2389.45768v2389.45768h-857.59346h-857.59346v-2389.45768z\" data-paper-data=\"{&quot;strokeWidth&quot;:1,&quot;rotation&quot;:0,&quot;deleteIcon&quot;:null,&quot;rotationIcon&quot;:null,&quot;group&quot;:null,&quot;editable&quot;:true,&quot;annotation&quot;:null}\" id=\"rectangle_a4876795-f994-4fd4-87b7-0842ed45e02c\" fill-opacity=\"0\" fill=\"#00bfff\" fill-rule=\"nonzero\" stroke=\"#00bfff\" stroke-width=\"1\" stroke-linecap=\"butt\" stroke-linejoin=\"miter\" stroke-miterlimit=\"10\" stroke-dasharray=\"\" stroke-dashoffset=\"0\" font-family=\"none\" font-weight=\"none\" font-size=\"none\" text-anchor=\"none\" style=\"mix-blend-mode: normal\"/></svg>"
                        }
                    },
                    "within": {
                        "@id": "https://diyhistory.org/uparl/omeka/oa/items/209/manifest.json",
                        "@type": "sc:Manifest"
                    }
                }
            ],
            "resource": [
                {
                    "@type": "dctypes:Text",
                    "chars": "<p><span style=\"font-size: 10pt; font-family: Arial;\" data-sheets-value=\"{&quot;1&quot;:2,&quot;2&quot;:&quot;星鳳樓帖-04-16&quot;}\" data-sheets-userformat=\"{&quot;2&quot;:513,&quot;3&quot;:[null,0],&quot;12&quot;:0}\">星鳳樓帖-04-16@東京大学</span></p>",
                    "format": "text/html"
                }
            ]
        },
        {
            "@context": "http://iiif.io/api/presentation/2/context.json",
            "@id": "https://diyhistory.org/uparl/omeka/oa/items/14707/anno.json",
            "@type": "oa:Annotation",
            "motivation": "oa:commenting",
            "on": [
                {
                    "@type": "oa:SpecificResource",
                    "full": "https://iiif.dl.itc.u-tokyo.ac.jp/repo/iiif/167779/canvas/p13",
                    "selector": {
                        "@type": "oa:Choice",
                        "default": {
                            "@type": "oa:FragmentSelector",
                            "value": "xywh=1184,827,1077,4816"
                        },
                        "item": {
                            "@type": "oa:SvgSelector",
                            "value": "<svg xmlns='http://www.w3.org/2000/svg'><path xmlns=\"http://www.w3.org/2000/svg\" d=\"M1184.37184,827.08243h538.7156v0h538.7156v2408.2152v2408.2152h-538.7156h-538.7156v-2408.2152z\" data-paper-data=\"{&quot;strokeWidth&quot;:1,&quot;rotation&quot;:0,&quot;deleteIcon&quot;:null,&quot;rotationIcon&quot;:null,&quot;group&quot;:null,&quot;editable&quot;:true,&quot;annotation&quot;:null}\" id=\"rectangle_e38f9d4e-92a0-4a1c-a3a3-1f7e82c5aa03\" fill-opacity=\"0\" fill=\"#00bfff\" fill-rule=\"nonzero\" stroke=\"#00bfff\" stroke-width=\"1\" stroke-linecap=\"butt\" stroke-linejoin=\"miter\" stroke-miterlimit=\"10\" stroke-dasharray=\"\" stroke-dashoffset=\"0\" font-family=\"none\" font-weight=\"none\" font-size=\"none\" text-anchor=\"none\" style=\"mix-blend-mode: normal\"/></svg>"
                        }
                    },
                    "within": {
                        "@id": "https://diyhistory.org/uparl/omeka/oa/items/209/manifest.json",
                        "@type": "sc:Manifest"
                    }
                }
            ],
            "resource": [
                {
                    "@type": "dctypes:Text",
                    "chars": "<p><span style=\"font-size: 10pt; font-family: Arial;\" data-sheets-value=\"{&quot;1&quot;:2,&quot;2&quot;:&quot;星鳳樓帖-04-17&quot;}\" data-sheets-userformat=\"{&quot;2&quot;:513,&quot;3&quot;:[null,0],&quot;12&quot;:0}\">星鳳樓帖-04-17@東京大学</span></p>",
                    "format": "text/html"
                }
            ]
        }
    ]
}