{
    "@id": "https://diyhistory.org/uparl/omeka/api/41.json",
    "added": "2017-11-06T19:23:27+00:00",
    "element_texts": [
        {
            "element": {
                "id": 50,
                "name": "Title",
                "resource": "elements",
                "url": "https://diyhistory.org/uparl/omeka/api/elements/50"
            },
            "element_set": {
                "id": 1,
                "name": "Dublin Core",
                "resource": "element_sets",
                "url": "https://diyhistory.org/uparl/omeka/api/element_sets/1"
            },
            "html": false,
            "text": "戯鴻堂法書 十五[A006096-15]"
        },
        {
            "element": {
                "id": 48,
                "name": "Source",
                "resource": "elements",
                "url": "https://diyhistory.org/uparl/omeka/api/elements/48"
            },
            "element_set": {
                "id": 1,
                "name": "Dublin Core",
                "resource": "element_sets",
                "url": "https://diyhistory.org/uparl/omeka/api/element_sets/1"
            },
            "html": false,
            "text": "https://iiif.dl.itc.u-tokyo.ac.jp/repo/iiif/167815/manifest"
        },
        {
            "element": {
                "id": 57,
                "name": "Original @id",
                "resource": "elements",
                "url": "https://diyhistory.org/uparl/omeka/api/elements/57"
            },
            "element_set": {
                "id": 6,
                "name": "IIIF Collection Metadata",
                "resource": "element_sets",
                "url": "https://diyhistory.org/uparl/omeka/api/element_sets/6"
            },
            "html": false,
            "text": "https://iiif.dl.itc.u-tokyo.ac.jp/repo/iiif/167815/manifest"
        },
        {
            "element": {
                "id": 58,
                "name": "IIIF Type",
                "resource": "elements",
                "url": "https://diyhistory.org/uparl/omeka/api/elements/58"
            },
            "element_set": {
                "id": 6,
                "name": "IIIF Collection Metadata",
                "resource": "element_sets",
                "url": "https://diyhistory.org/uparl/omeka/api/element_sets/6"
            },
            "html": false,
            "text": "Manifest"
        },
        {
            "element": {
                "id": 59,
                "name": "JSON Data",
                "resource": "elements",
                "url": "https://diyhistory.org/uparl/omeka/api/elements/59"
            },
            "element_set": {
                "id": 6,
                "name": "IIIF Collection Metadata",
                "resource": "element_sets",
                "url": "https://diyhistory.org/uparl/omeka/api/element_sets/6"
            },
            "html": false,
            "text": "{\"within\": \"https://iiif.dl.itc.u-tokyo.ac.jp/repo/s/uparl/\", \"attribution\": \"東京大学附属図書館アジア研究図書館上廣倫理財団寄付研究部門 / Uehiro Project for the Asian Research Library in the University of Tokyo, JAPAN\", \"license\": \"http://creativecommons.org/licenses/by-nc-sa/4.0/\", \"seeAlso\": \"https://iiif.dl.itc.u-tokyo.ac.jp/repo/api/items/167815\", \"@id\": \"https://iiif.dl.itc.u-tokyo.ac.jp/repo/iiif/167815/manifest\", \"viewingDirection\": \"right-to-left\", \"metadata\": [{\"value\": \"戯鴻堂法書 十五[A006096-15]\", \"label\": \"Title\"}, {\"value\": \"024ce989-a34d-4a1d-87a7-332ca7f578c6\", \"label\": \"identifier\"}, {\"value\": \"https://iiif.dl.itc.u-tokyo.ac.jp/repo/iiif/167815/manifest\", \"label\": \"Manifest Uri\"}, {\"value\": \"漢籍・碑帖拓本資料\", \"label\": \"Database Label\"}, {\"value\": \"東京大学附属図書館アジア研究図書館上廣倫理財団寄付研究部門 / Uehiro Project for the Asian Research Library in the University of Tokyo, JAPAN\", \"label\": \"attributionLabel\"}, {\"value\": \"A006096-15\", \"label\": \"Sort\"}, {\"value\": \"A006096\", \"label\": \"データの識別子\"}, {\"value\": \"(巻首題)戯鴻堂法書\", \"label\": \"著作のタイトル\"}, {\"value\": \"(明)董其昌輯\", \"label\": \"著作の責任\"}, {\"value\": \"(明)万暦31年\", \"label\": \"著作の時期\"}, {\"value\": \"1603年\", \"label\": \"著作の年\"}, {\"value\": \"16巻\", \"label\": \"著作の構成\"}, {\"value\": \"(明)董其昌刻\", \"label\": \"バージョンの責任\"}, {\"value\": \"(明)万暦31年\", \"label\": \"バージョンの成立時期\"}, {\"value\": \"1603年\", \"label\": \"バージョンの成立年\"}, {\"value\": \"松江府華亭県\", \"label\": \"バージョンの成立場所\"}, {\"value\": \"石刻\", \"label\": \"バージョンの技法\"}, {\"value\": \"拓本\", \"label\": \"資料化の技法\"}, {\"value\": \"16冊\", \"label\": \"数量\"}, {\"value\": \"折帖装\", \"label\": \"装訂\"}, {\"value\": \"28.4×14.9cm\", \"label\": \"大きさ（縦×横）\"}, {\"value\": \"東京帝国大学図書印, 明倫堂図書, 渡辺氏図書記\", \"label\": \"印記\"}, {\"value\": \"渡辺信旧蔵, 東京大学総合図書館所蔵\", \"label\": \"出所\"}, {\"value\": \"A00-6096\", \"label\": \"請求記号\"}, {\"value\": \"宇野雪村『法帖事典』上 : 本論編, 東京, 雄山閣, 1984, pp.111-112\", \"label\": \"参考文献\"}], \"related\": \"https://iiif.dl.itc.u-tokyo.ac.jp/repo/s/uparl/document/024ce989-a34d-4a1d-87a7-332ca7f578c6\", \"label\": \"戯鴻堂法書 十五[A006096-15]\", \"logo\": \"https://iiif.dl.itc.u-tokyo.ac.jp/images/ut-logo.jpg\", \"thumbnail\": \"https://iiif.dl.itc.u-tokyo.ac.jp/repo/files/square/167815/default.jpg\", \"@type\": \"sc:Manifest\", \"@context\": \"http://iiif.io/api/presentation/2/context.json\", \"sequences\": [{\"canvases\": [{\"@type\": \"sc:Canvas\", \"thumbnail\": {\"service\": {\"profile\": \"http://iiif.io/api/image/2/level2.json\", \"@context\": \"http://iiif.io/api/image/2/context.json\", \"@id\": \"https://iiif.dl.itc.u-tokyo.ac.jp/repo/iiif-img/168749\"}, \"@id\": \"https://iiif.dl.itc.u-tokyo.ac.jp/repo/iiif-img/168749/full/200,200/0/default.jpg\"}, \"width\": 7362, \"@id\": \"https://iiif.dl.itc.u-tokyo.ac.jp/repo/iiif/167815/canvas/p1\", \"height\": 6132, \"images\": [{\"motivation\": \"sc:painting\", \"@type\": \"oa:Annotation\", \"resource\": {\"@type\": \"dctypes:Image\", \"format\": \"image/jpeg\", \"width\": 7362, \"@id\": \"https://iiif.dl.itc.u-tokyo.ac.jp/repo/iiif-img/168749\", \"height\": 6132, \"service\": {\"profile\": \"http://iiif.io/api/image/2/level2.json\", \"tiles\": [{\"width\": 256, \"scaleFactors\": [1, 2, 4, 8, 16, 32]}], \"width\": 7362, \"@id\": \"https://iiif.dl.itc.u-tokyo.ac.jp/repo/iiif-img/168749\", \"@context\": \"http://iiif.io/api/image/2/context.json\", \"height\": 6132}}, \"on\": \"https://iiif.dl.itc.u-tokyo.ac.jp/repo/iiif/167815/canvas/p1\", \"@id\": \"https://iiif.dl.itc.u-tokyo.ac.jp/repo/iiif/167815/annotation/p0001-image\"}], \"label\": \"[1]\"}, {\"@type\": \"sc:Canvas\", \"thumbnail\": {\"service\": {\"profile\": \"http://iiif.io/api/image/2/level2.json\", \"@context\": \"http://iiif.io/api/image/2/context.json\", \"@id\": \"https://iiif.dl.itc.u-tokyo.ac.jp/repo/iiif-img/168750\"}, \"@id\": \"https://iiif.dl.itc.u-tokyo.ac.jp/repo/iiif-img/168750/full/200,200/0/default.jpg\"}, \"width\": 7362, \"@id\": \"https://iiif.dl.itc.u-tokyo.ac.jp/repo/iiif/167815/canvas/p2\", \"height\": 6132, \"images\": [{\"motivation\": \"sc:painting\", \"@type\": \"oa:Annotation\", \"resource\": {\"@type\": \"dctypes:Image\", \"format\": \"image/jpeg\", \"width\": 7362, \"@id\": \"https://iiif.dl.itc.u-tokyo.ac.jp/repo/iiif-img/168750\", \"height\": 6132, \"service\": {\"profile\": \"http://iiif.io/api/image/2/level2.json\", \"tiles\": [{\"width\": 256, \"scaleFactors\": [1, 2, 4, 8, 16, 32]}], \"width\": 7362, \"@id\": \"https://iiif.dl.itc.u-tokyo.ac.jp/repo/iiif-img/168750\", \"@context\": \"http://iiif.io/api/image/2/context.json\", \"height\": 6132}}, \"on\": \"https://iiif.dl.itc.u-tokyo.ac.jp/repo/iiif/167815/canvas/p2\", \"@id\": \"https://iiif.dl.itc.u-tokyo.ac.jp/repo/iiif/167815/annotation/p0002-image\"}], \"label\": \"[2]\"}, {\"@type\": \"sc:Canvas\", \"thumbnail\": {\"service\": {\"profile\": \"http://iiif.io/api/image/2/level2.json\", \"@context\": \"http://iiif.io/api/image/2/context.json\", \"@id\": \"https://iiif.dl.itc.u-tokyo.ac.jp/repo/iiif-img/168751\"}, \"@id\": \"https://iiif.dl.itc.u-tokyo.ac.jp/repo/iiif-img/168751/full/200,200/0/default.jpg\"}, \"width\": 7362, \"@id\": \"https://iiif.dl.itc.u-tokyo.ac.jp/repo/iiif/167815/canvas/p3\", \"height\": 6132, \"images\": [{\"motivation\": \"sc:painting\", \"@type\": \"oa:Annotation\", \"resource\": {\"@type\": \"dctypes:Image\", \"format\": \"image/jpeg\", \"width\": 7362, \"@id\": \"https://iiif.dl.itc.u-tokyo.ac.jp/repo/iiif-img/168751\", \"height\": 6132, \"service\": {\"profile\": \"http://iiif.io/api/image/2/level2.json\", \"tiles\": [{\"width\": 256, \"scaleFactors\": [1, 2, 4, 8, 16, 32]}], \"width\": 7362, \"@id\": \"https://iiif.dl.itc.u-tokyo.ac.jp/repo/iiif-img/168751\", \"@context\": \"http://iiif.io/api/image/2/context.json\", \"height\": 6132}}, \"on\": \"https://iiif.dl.itc.u-tokyo.ac.jp/repo/iiif/167815/canvas/p3\", \"@id\": \"https://iiif.dl.itc.u-tokyo.ac.jp/repo/iiif/167815/annotation/p0003-image\"}], \"label\": \"[3]\"}, {\"@type\": \"sc:Canvas\", \"thumbnail\": {\"service\": {\"profile\": \"http://iiif.io/api/image/2/level2.json\", \"@context\": \"http://iiif.io/api/image/2/context.json\", \"@id\": \"https://iiif.dl.itc.u-tokyo.ac.jp/repo/iiif-img/168752\"}, \"@id\": \"https://iiif.dl.itc.u-tokyo.ac.jp/repo/iiif-img/168752/full/200,200/0/default.jpg\"}, \"width\": 7362, \"@id\": \"https://iiif.dl.itc.u-tokyo.ac.jp/repo/iiif/167815/canvas/p4\", \"height\": 6132, \"images\": [{\"motivation\": \"sc:painting\", \"@type\": \"oa:Annotation\", \"resource\": {\"@type\": \"dctypes:Image\", \"format\": \"image/jpeg\", \"width\": 7362, \"@id\": \"https://iiif.dl.itc.u-tokyo.ac.jp/repo/iiif-img/168752\", \"height\": 6132, \"service\": {\"profile\": \"http://iiif.io/api/image/2/level2.json\", \"tiles\": [{\"width\": 256, \"scaleFactors\": [1, 2, 4, 8, 16, 32]}], \"width\": 7362, \"@id\": \"https://iiif.dl.itc.u-tokyo.ac.jp/repo/iiif-img/168752\", \"@context\": \"http://iiif.io/api/image/2/context.json\", \"height\": 6132}}, \"on\": \"https://iiif.dl.itc.u-tokyo.ac.jp/repo/iiif/167815/canvas/p4\", \"@id\": \"https://iiif.dl.itc.u-tokyo.ac.jp/repo/iiif/167815/annotation/p0004-image\"}], \"label\": \"[4]\"}, {\"@type\": \"sc:Canvas\", \"thumbnail\": {\"service\": {\"profile\": \"http://iiif.io/api/image/2/level2.json\", \"@context\": \"http://iiif.io/api/image/2/context.json\", \"@id\": \"https://iiif.dl.itc.u-tokyo.ac.jp/repo/iiif-img/168753\"}, \"@id\": \"https://iiif.dl.itc.u-tokyo.ac.jp/repo/iiif-img/168753/full/200,200/0/default.jpg\"}, \"width\": 7362, \"@id\": \"https://iiif.dl.itc.u-tokyo.ac.jp/repo/iiif/167815/canvas/p5\", \"height\": 6132, \"images\": [{\"motivation\": \"sc:painting\", \"@type\": \"oa:Annotation\", \"resource\": {\"@type\": \"dctypes:Image\", \"format\": \"image/jpeg\", \"width\": 7362, \"@id\": \"https://iiif.dl.itc.u-tokyo.ac.jp/repo/iiif-img/168753\", \"height\": 6132, \"service\": {\"profile\": \"http://iiif.io/api/image/2/level2.json\", \"tiles\": [{\"width\": 256, \"scaleFactors\": [1, 2, 4, 8, 16, 32]}], \"width\": 7362, \"@id\": \"https://iiif.dl.itc.u-tokyo.ac.jp/repo/iiif-img/168753\", \"@context\": \"http://iiif.io/api/image/2/context.json\", \"height\": 6132}}, \"on\": \"https://iiif.dl.itc.u-tokyo.ac.jp/repo/iiif/167815/canvas/p5\", \"@id\": \"https://iiif.dl.itc.u-tokyo.ac.jp/repo/iiif/167815/annotation/p0005-image\"}], \"label\": \"[5]\"}, {\"@type\": \"sc:Canvas\", \"thumbnail\": {\"service\": {\"profile\": \"http://iiif.io/api/image/2/level2.json\", \"@context\": \"http://iiif.io/api/image/2/context.json\", \"@id\": \"https://iiif.dl.itc.u-tokyo.ac.jp/repo/iiif-img/168754\"}, \"@id\": \"https://iiif.dl.itc.u-tokyo.ac.jp/repo/iiif-img/168754/full/200,200/0/default.jpg\"}, \"width\": 7362, \"@id\": \"https://iiif.dl.itc.u-tokyo.ac.jp/repo/iiif/167815/canvas/p6\", \"height\": 6132, \"images\": [{\"motivation\": \"sc:painting\", \"@type\": \"oa:Annotation\", \"resource\": {\"@type\": \"dctypes:Image\", \"format\": \"image/jpeg\", \"width\": 7362, \"@id\": \"https://iiif.dl.itc.u-tokyo.ac.jp/repo/iiif-img/168754\", \"height\": 6132, \"service\": {\"profile\": \"http://iiif.io/api/image/2/level2.json\", \"tiles\": [{\"width\": 256, \"scaleFactors\": [1, 2, 4, 8, 16, 32]}], \"width\": 7362, \"@id\": \"https://iiif.dl.itc.u-tokyo.ac.jp/repo/iiif-img/168754\", \"@context\": \"http://iiif.io/api/image/2/context.json\", \"height\": 6132}}, \"on\": \"https://iiif.dl.itc.u-tokyo.ac.jp/repo/iiif/167815/canvas/p6\", \"@id\": \"https://iiif.dl.itc.u-tokyo.ac.jp/repo/iiif/167815/annotation/p0006-image\"}], \"label\": \"[6]\"}, {\"@type\": \"sc:Canvas\", \"thumbnail\": {\"service\": {\"profile\": \"http://iiif.io/api/image/2/level2.json\", \"@context\": \"http://iiif.io/api/image/2/context.json\", \"@id\": \"https://iiif.dl.itc.u-tokyo.ac.jp/repo/iiif-img/168755\"}, \"@id\": \"https://iiif.dl.itc.u-tokyo.ac.jp/repo/iiif-img/168755/full/200,200/0/default.jpg\"}, \"width\": 7362, \"@id\": \"https://iiif.dl.itc.u-tokyo.ac.jp/repo/iiif/167815/canvas/p7\", \"height\": 6132, \"images\": [{\"motivation\": \"sc:painting\", \"@type\": \"oa:Annotation\", \"resource\": {\"@type\": \"dctypes:Image\", \"format\": \"image/jpeg\", \"width\": 7362, \"@id\": \"https://iiif.dl.itc.u-tokyo.ac.jp/repo/iiif-img/168755\", \"height\": 6132, \"service\": {\"profile\": \"http://iiif.io/api/image/2/level2.json\", \"tiles\": [{\"width\": 256, \"scaleFactors\": [1, 2, 4, 8, 16, 32]}], \"width\": 7362, \"@id\": \"https://iiif.dl.itc.u-tokyo.ac.jp/repo/iiif-img/168755\", \"@context\": \"http://iiif.io/api/image/2/context.json\", \"height\": 6132}}, \"on\": \"https://iiif.dl.itc.u-tokyo.ac.jp/repo/iiif/167815/canvas/p7\", \"@id\": \"https://iiif.dl.itc.u-tokyo.ac.jp/repo/iiif/167815/annotation/p0007-image\"}], \"label\": \"[7]\"}, {\"@type\": \"sc:Canvas\", \"thumbnail\": {\"service\": {\"profile\": \"http://iiif.io/api/image/2/level2.json\", \"@context\": \"http://iiif.io/api/image/2/context.json\", \"@id\": \"https://iiif.dl.itc.u-tokyo.ac.jp/repo/iiif-img/168756\"}, \"@id\": \"https://iiif.dl.itc.u-tokyo.ac.jp/repo/iiif-img/168756/full/200,200/0/default.jpg\"}, \"width\": 7362, \"@id\": \"https://iiif.dl.itc.u-tokyo.ac.jp/repo/iiif/167815/canvas/p8\", \"height\": 6132, \"images\": [{\"motivation\": \"sc:painting\", \"@type\": \"oa:Annotation\", \"resource\": {\"@type\": \"dctypes:Image\", \"format\": \"image/jpeg\", \"width\": 7362, \"@id\": \"https://iiif.dl.itc.u-tokyo.ac.jp/repo/iiif-img/168756\", \"height\": 6132, \"service\": {\"profile\": \"http://iiif.io/api/image/2/level2.json\", \"tiles\": [{\"width\": 256, \"scaleFactors\": [1, 2, 4, 8, 16, 32]}], \"width\": 7362, \"@id\": \"https://iiif.dl.itc.u-tokyo.ac.jp/repo/iiif-img/168756\", \"@context\": \"http://iiif.io/api/image/2/context.json\", \"height\": 6132}}, \"on\": \"https://iiif.dl.itc.u-tokyo.ac.jp/repo/iiif/167815/canvas/p8\", \"@id\": \"https://iiif.dl.itc.u-tokyo.ac.jp/repo/iiif/167815/annotation/p0008-image\"}], \"label\": \"[8]\"}, {\"@type\": \"sc:Canvas\", \"thumbnail\": {\"service\": {\"profile\": \"http://iiif.io/api/image/2/level2.json\", \"@context\": \"http://iiif.io/api/image/2/context.json\", \"@id\": \"https://iiif.dl.itc.u-tokyo.ac.jp/repo/iiif-img/168757\"}, \"@id\": \"https://iiif.dl.itc.u-tokyo.ac.jp/repo/iiif-img/168757/full/200,200/0/default.jpg\"}, \"width\": 7362, \"@id\": \"https://iiif.dl.itc.u-tokyo.ac.jp/repo/iiif/167815/canvas/p9\", \"height\": 6132, \"images\": [{\"motivation\": \"sc:painting\", \"@type\": \"oa:Annotation\", \"resource\": {\"@type\": \"dctypes:Image\", \"format\": \"image/jpeg\", \"width\": 7362, \"@id\": \"https://iiif.dl.itc.u-tokyo.ac.jp/repo/iiif-img/168757\", \"height\": 6132, \"service\": {\"profile\": \"http://iiif.io/api/image/2/level2.json\", \"tiles\": [{\"width\": 256, \"scaleFactors\": [1, 2, 4, 8, 16, 32]}], \"width\": 7362, \"@id\": \"https://iiif.dl.itc.u-tokyo.ac.jp/repo/iiif-img/168757\", \"@context\": \"http://iiif.io/api/image/2/context.json\", \"height\": 6132}}, \"on\": \"https://iiif.dl.itc.u-tokyo.ac.jp/repo/iiif/167815/canvas/p9\", \"@id\": \"https://iiif.dl.itc.u-tokyo.ac.jp/repo/iiif/167815/annotation/p0009-image\"}], \"label\": \"[9]\"}, {\"@type\": \"sc:Canvas\", \"thumbnail\": {\"service\": {\"profile\": \"http://iiif.io/api/image/2/level2.json\", \"@context\": \"http://iiif.io/api/image/2/context.json\", \"@id\": \"https://iiif.dl.itc.u-tokyo.ac.jp/repo/iiif-img/168758\"}, \"@id\": \"https://iiif.dl.itc.u-tokyo.ac.jp/repo/iiif-img/168758/full/200,200/0/default.jpg\"}, \"width\": 7362, \"@id\": \"https://iiif.dl.itc.u-tokyo.ac.jp/repo/iiif/167815/canvas/p10\", \"height\": 6132, \"images\": [{\"motivation\": \"sc:painting\", \"@type\": \"oa:Annotation\", \"resource\": {\"@type\": \"dctypes:Image\", \"format\": \"image/jpeg\", \"width\": 7362, \"@id\": \"https://iiif.dl.itc.u-tokyo.ac.jp/repo/iiif-img/168758\", \"height\": 6132, \"service\": {\"profile\": \"http://iiif.io/api/image/2/level2.json\", \"tiles\": [{\"width\": 256, \"scaleFactors\": [1, 2, 4, 8, 16, 32]}], \"width\": 7362, \"@id\": \"https://iiif.dl.itc.u-tokyo.ac.jp/repo/iiif-img/168758\", \"@context\": \"http://iiif.io/api/image/2/context.json\", \"height\": 6132}}, \"on\": \"https://iiif.dl.itc.u-tokyo.ac.jp/repo/iiif/167815/canvas/p10\", \"@id\": \"https://iiif.dl.itc.u-tokyo.ac.jp/repo/iiif/167815/annotation/p0010-image\"}], \"label\": \"[10]\"}, {\"@type\": \"sc:Canvas\", \"thumbnail\": {\"service\": {\"profile\": \"http://iiif.io/api/image/2/level2.json\", \"@context\": \"http://iiif.io/api/image/2/context.json\", \"@id\": \"https://iiif.dl.itc.u-tokyo.ac.jp/repo/iiif-img/168759\"}, \"@id\": \"https://iiif.dl.itc.u-tokyo.ac.jp/repo/iiif-img/168759/full/200,200/0/default.jpg\"}, \"width\": 7362, \"@id\": \"https://iiif.dl.itc.u-tokyo.ac.jp/repo/iiif/167815/canvas/p11\", \"height\": 6132, \"images\": [{\"motivation\": \"sc:painting\", \"@type\": \"oa:Annotation\", \"resource\": {\"@type\": \"dctypes:Image\", \"format\": \"image/jpeg\", \"width\": 7362, \"@id\": \"https://iiif.dl.itc.u-tokyo.ac.jp/repo/iiif-img/168759\", \"height\": 6132, \"service\": {\"profile\": \"http://iiif.io/api/image/2/level2.json\", \"tiles\": [{\"width\": 256, \"scaleFactors\": [1, 2, 4, 8, 16, 32]}], \"width\": 7362, \"@id\": \"https://iiif.dl.itc.u-tokyo.ac.jp/repo/iiif-img/168759\", \"@context\": \"http://iiif.io/api/image/2/context.json\", \"height\": 6132}}, \"on\": \"https://iiif.dl.itc.u-tokyo.ac.jp/repo/iiif/167815/canvas/p11\", \"@id\": \"https://iiif.dl.itc.u-tokyo.ac.jp/repo/iiif/167815/annotation/p0011-image\"}], \"label\": \"[11]\"}, {\"@type\": \"sc:Canvas\", \"thumbnail\": {\"service\": {\"profile\": \"http://iiif.io/api/image/2/level2.json\", \"@context\": \"http://iiif.io/api/image/2/context.json\", \"@id\": \"https://iiif.dl.itc.u-tokyo.ac.jp/repo/iiif-img/168760\"}, \"@id\": \"https://iiif.dl.itc.u-tokyo.ac.jp/repo/iiif-img/168760/full/200,200/0/default.jpg\"}, \"width\": 7362, \"@id\": \"https://iiif.dl.itc.u-tokyo.ac.jp/repo/iiif/167815/canvas/p12\", \"height\": 6132, \"images\": [{\"motivation\": \"sc:painting\", \"@type\": \"oa:Annotation\", \"resource\": {\"@type\": \"dctypes:Image\", \"format\": \"image/jpeg\", \"width\": 7362, \"@id\": \"https://iiif.dl.itc.u-tokyo.ac.jp/repo/iiif-img/168760\", \"height\": 6132, \"service\": {\"profile\": \"http://iiif.io/api/image/2/level2.json\", \"tiles\": [{\"width\": 256, \"scaleFactors\": [1, 2, 4, 8, 16, 32]}], \"width\": 7362, \"@id\": \"https://iiif.dl.itc.u-tokyo.ac.jp/repo/iiif-img/168760\", \"@context\": \"http://iiif.io/api/image/2/context.json\", \"height\": 6132}}, \"on\": \"https://iiif.dl.itc.u-tokyo.ac.jp/repo/iiif/167815/canvas/p12\", \"@id\": \"https://iiif.dl.itc.u-tokyo.ac.jp/repo/iiif/167815/annotation/p0012-image\"}], \"label\": \"[12]\"}, {\"@type\": \"sc:Canvas\", \"thumbnail\": {\"service\": {\"profile\": \"http://iiif.io/api/image/2/level2.json\", \"@context\": \"http://iiif.io/api/image/2/context.json\", \"@id\": \"https://iiif.dl.itc.u-tokyo.ac.jp/repo/iiif-img/168761\"}, \"@id\": \"https://iiif.dl.itc.u-tokyo.ac.jp/repo/iiif-img/168761/full/200,200/0/default.jpg\"}, \"width\": 7362, \"@id\": \"https://iiif.dl.itc.u-tokyo.ac.jp/repo/iiif/167815/canvas/p13\", \"height\": 6132, \"images\": [{\"motivation\": \"sc:painting\", \"@type\": \"oa:Annotation\", \"resource\": {\"@type\": \"dctypes:Image\", \"format\": \"image/jpeg\", \"width\": 7362, \"@id\": \"https://iiif.dl.itc.u-tokyo.ac.jp/repo/iiif-img/168761\", \"height\": 6132, \"service\": {\"profile\": \"http://iiif.io/api/image/2/level2.json\", \"tiles\": [{\"width\": 256, \"scaleFactors\": [1, 2, 4, 8, 16, 32]}], \"width\": 7362, \"@id\": \"https://iiif.dl.itc.u-tokyo.ac.jp/repo/iiif-img/168761\", \"@context\": \"http://iiif.io/api/image/2/context.json\", \"height\": 6132}}, \"on\": \"https://iiif.dl.itc.u-tokyo.ac.jp/repo/iiif/167815/canvas/p13\", \"@id\": \"https://iiif.dl.itc.u-tokyo.ac.jp/repo/iiif/167815/annotation/p0013-image\"}], \"label\": \"[13]\"}, {\"@type\": \"sc:Canvas\", \"thumbnail\": {\"service\": {\"profile\": \"http://iiif.io/api/image/2/level2.json\", \"@context\": \"http://iiif.io/api/image/2/context.json\", \"@id\": \"https://iiif.dl.itc.u-tokyo.ac.jp/repo/iiif-img/168762\"}, \"@id\": \"https://iiif.dl.itc.u-tokyo.ac.jp/repo/iiif-img/168762/full/200,200/0/default.jpg\"}, \"width\": 7362, \"@id\": \"https://iiif.dl.itc.u-tokyo.ac.jp/repo/iiif/167815/canvas/p14\", \"height\": 6132, \"images\": [{\"motivation\": \"sc:painting\", \"@type\": \"oa:Annotation\", \"resource\": {\"@type\": \"dctypes:Image\", \"format\": \"image/jpeg\", \"width\": 7362, \"@id\": \"https://iiif.dl.itc.u-tokyo.ac.jp/repo/iiif-img/168762\", \"height\": 6132, \"service\": {\"profile\": \"http://iiif.io/api/image/2/level2.json\", \"tiles\": [{\"width\": 256, \"scaleFactors\": [1, 2, 4, 8, 16, 32]}], \"width\": 7362, \"@id\": \"https://iiif.dl.itc.u-tokyo.ac.jp/repo/iiif-img/168762\", \"@context\": \"http://iiif.io/api/image/2/context.json\", \"height\": 6132}}, \"on\": \"https://iiif.dl.itc.u-tokyo.ac.jp/repo/iiif/167815/canvas/p14\", \"@id\": \"https://iiif.dl.itc.u-tokyo.ac.jp/repo/iiif/167815/annotation/p0014-image\"}], \"label\": \"[14]\"}, {\"@type\": \"sc:Canvas\", \"thumbnail\": {\"service\": {\"profile\": \"http://iiif.io/api/image/2/level2.json\", \"@context\": \"http://iiif.io/api/image/2/context.json\", \"@id\": \"https://iiif.dl.itc.u-tokyo.ac.jp/repo/iiif-img/168763\"}, \"@id\": \"https://iiif.dl.itc.u-tokyo.ac.jp/repo/iiif-img/168763/full/200,200/0/default.jpg\"}, \"width\": 7362, \"@id\": \"https://iiif.dl.itc.u-tokyo.ac.jp/repo/iiif/167815/canvas/p15\", \"height\": 6132, \"images\": [{\"motivation\": \"sc:painting\", \"@type\": \"oa:Annotation\", \"resource\": {\"@type\": \"dctypes:Image\", \"format\": \"image/jpeg\", \"width\": 7362, \"@id\": \"https://iiif.dl.itc.u-tokyo.ac.jp/repo/iiif-img/168763\", \"height\": 6132, \"service\": {\"profile\": \"http://iiif.io/api/image/2/level2.json\", \"tiles\": [{\"width\": 256, \"scaleFactors\": [1, 2, 4, 8, 16, 32]}], \"width\": 7362, \"@id\": \"https://iiif.dl.itc.u-tokyo.ac.jp/repo/iiif-img/168763\", \"@context\": \"http://iiif.io/api/image/2/context.json\", \"height\": 6132}}, \"on\": \"https://iiif.dl.itc.u-tokyo.ac.jp/repo/iiif/167815/canvas/p15\", \"@id\": \"https://iiif.dl.itc.u-tokyo.ac.jp/repo/iiif/167815/annotation/p0015-image\"}], \"label\": \"[15]\"}, {\"@type\": \"sc:Canvas\", \"thumbnail\": {\"service\": {\"profile\": \"http://iiif.io/api/image/2/level2.json\", \"@context\": \"http://iiif.io/api/image/2/context.json\", \"@id\": \"https://iiif.dl.itc.u-tokyo.ac.jp/repo/iiif-img/168764\"}, \"@id\": \"https://iiif.dl.itc.u-tokyo.ac.jp/repo/iiif-img/168764/full/200,200/0/default.jpg\"}, \"width\": 7362, \"@id\": \"https://iiif.dl.itc.u-tokyo.ac.jp/repo/iiif/167815/canvas/p16\", \"height\": 6132, \"images\": [{\"motivation\": \"sc:painting\", \"@type\": \"oa:Annotation\", \"resource\": {\"@type\": \"dctypes:Image\", \"format\": \"image/jpeg\", \"width\": 7362, \"@id\": \"https://iiif.dl.itc.u-tokyo.ac.jp/repo/iiif-img/168764\", \"height\": 6132, \"service\": {\"profile\": \"http://iiif.io/api/image/2/level2.json\", \"tiles\": [{\"width\": 256, \"scaleFactors\": [1, 2, 4, 8, 16, 32]}], \"width\": 7362, \"@id\": \"https://iiif.dl.itc.u-tokyo.ac.jp/repo/iiif-img/168764\", \"@context\": \"http://iiif.io/api/image/2/context.json\", \"height\": 6132}}, \"on\": \"https://iiif.dl.itc.u-tokyo.ac.jp/repo/iiif/167815/canvas/p16\", \"@id\": \"https://iiif.dl.itc.u-tokyo.ac.jp/repo/iiif/167815/annotation/p0016-image\"}], \"label\": \"[16]\"}, {\"@type\": \"sc:Canvas\", \"thumbnail\": {\"service\": {\"profile\": \"http://iiif.io/api/image/2/level2.json\", \"@context\": \"http://iiif.io/api/image/2/context.json\", \"@id\": \"https://iiif.dl.itc.u-tokyo.ac.jp/repo/iiif-img/168765\"}, \"@id\": \"https://iiif.dl.itc.u-tokyo.ac.jp/repo/iiif-img/168765/full/200,200/0/default.jpg\"}, \"width\": 7362, \"@id\": \"https://iiif.dl.itc.u-tokyo.ac.jp/repo/iiif/167815/canvas/p17\", \"height\": 6132, \"images\": [{\"motivation\": \"sc:painting\", \"@type\": \"oa:Annotation\", \"resource\": {\"@type\": \"dctypes:Image\", \"format\": \"image/jpeg\", \"width\": 7362, \"@id\": \"https://iiif.dl.itc.u-tokyo.ac.jp/repo/iiif-img/168765\", \"height\": 6132, \"service\": {\"profile\": \"http://iiif.io/api/image/2/level2.json\", \"tiles\": [{\"width\": 256, \"scaleFactors\": [1, 2, 4, 8, 16, 32]}], \"width\": 7362, \"@id\": \"https://iiif.dl.itc.u-tokyo.ac.jp/repo/iiif-img/168765\", \"@context\": \"http://iiif.io/api/image/2/context.json\", \"height\": 6132}}, \"on\": \"https://iiif.dl.itc.u-tokyo.ac.jp/repo/iiif/167815/canvas/p17\", \"@id\": \"https://iiif.dl.itc.u-tokyo.ac.jp/repo/iiif/167815/annotation/p0017-image\"}], \"label\": \"[17]\"}, {\"@type\": \"sc:Canvas\", \"thumbnail\": {\"service\": {\"profile\": \"http://iiif.io/api/image/2/level2.json\", \"@context\": \"http://iiif.io/api/image/2/context.json\", \"@id\": \"https://iiif.dl.itc.u-tokyo.ac.jp/repo/iiif-img/168766\"}, \"@id\": \"https://iiif.dl.itc.u-tokyo.ac.jp/repo/iiif-img/168766/full/200,200/0/default.jpg\"}, \"width\": 7362, \"@id\": \"https://iiif.dl.itc.u-tokyo.ac.jp/repo/iiif/167815/canvas/p18\", \"height\": 6132, \"images\": [{\"motivation\": \"sc:painting\", \"@type\": \"oa:Annotation\", \"resource\": {\"@type\": \"dctypes:Image\", \"format\": \"image/jpeg\", \"width\": 7362, \"@id\": \"https://iiif.dl.itc.u-tokyo.ac.jp/repo/iiif-img/168766\", \"height\": 6132, \"service\": {\"profile\": \"http://iiif.io/api/image/2/level2.json\", \"tiles\": [{\"width\": 256, \"scaleFactors\": [1, 2, 4, 8, 16, 32]}], \"width\": 7362, \"@id\": \"https://iiif.dl.itc.u-tokyo.ac.jp/repo/iiif-img/168766\", \"@context\": \"http://iiif.io/api/image/2/context.json\", \"height\": 6132}}, \"on\": \"https://iiif.dl.itc.u-tokyo.ac.jp/repo/iiif/167815/canvas/p18\", \"@id\": \"https://iiif.dl.itc.u-tokyo.ac.jp/repo/iiif/167815/annotation/p0018-image\"}], \"label\": \"[18]\"}, {\"@type\": \"sc:Canvas\", \"thumbnail\": {\"service\": {\"profile\": \"http://iiif.io/api/image/2/level2.json\", \"@context\": \"http://iiif.io/api/image/2/context.json\", \"@id\": \"https://iiif.dl.itc.u-tokyo.ac.jp/repo/iiif-img/168767\"}, \"@id\": \"https://iiif.dl.itc.u-tokyo.ac.jp/repo/iiif-img/168767/full/200,200/0/default.jpg\"}, \"width\": 7362, \"@id\": \"https://iiif.dl.itc.u-tokyo.ac.jp/repo/iiif/167815/canvas/p19\", \"height\": 6132, \"images\": [{\"motivation\": \"sc:painting\", \"@type\": \"oa:Annotation\", \"resource\": {\"@type\": \"dctypes:Image\", \"format\": \"image/jpeg\", \"width\": 7362, \"@id\": \"https://iiif.dl.itc.u-tokyo.ac.jp/repo/iiif-img/168767\", \"height\": 6132, \"service\": {\"profile\": \"http://iiif.io/api/image/2/level2.json\", \"tiles\": [{\"width\": 256, \"scaleFactors\": [1, 2, 4, 8, 16, 32]}], \"width\": 7362, \"@id\": \"https://iiif.dl.itc.u-tokyo.ac.jp/repo/iiif-img/168767\", \"@context\": \"http://iiif.io/api/image/2/context.json\", \"height\": 6132}}, \"on\": \"https://iiif.dl.itc.u-tokyo.ac.jp/repo/iiif/167815/canvas/p19\", \"@id\": \"https://iiif.dl.itc.u-tokyo.ac.jp/repo/iiif/167815/annotation/p0019-image\"}], \"label\": \"[19]\"}, {\"@type\": \"sc:Canvas\", \"thumbnail\": {\"service\": {\"profile\": \"http://iiif.io/api/image/2/level2.json\", \"@context\": \"http://iiif.io/api/image/2/context.json\", \"@id\": \"https://iiif.dl.itc.u-tokyo.ac.jp/repo/iiif-img/168768\"}, \"@id\": \"https://iiif.dl.itc.u-tokyo.ac.jp/repo/iiif-img/168768/full/200,200/0/default.jpg\"}, \"width\": 7362, \"@id\": \"https://iiif.dl.itc.u-tokyo.ac.jp/repo/iiif/167815/canvas/p20\", \"height\": 6132, \"images\": [{\"motivation\": \"sc:painting\", \"@type\": \"oa:Annotation\", \"resource\": {\"@type\": \"dctypes:Image\", \"format\": \"image/jpeg\", \"width\": 7362, \"@id\": \"https://iiif.dl.itc.u-tokyo.ac.jp/repo/iiif-img/168768\", \"height\": 6132, \"service\": {\"profile\": \"http://iiif.io/api/image/2/level2.json\", \"tiles\": [{\"width\": 256, \"scaleFactors\": [1, 2, 4, 8, 16, 32]}], \"width\": 7362, \"@id\": \"https://iiif.dl.itc.u-tokyo.ac.jp/repo/iiif-img/168768\", \"@context\": \"http://iiif.io/api/image/2/context.json\", \"height\": 6132}}, \"on\": \"https://iiif.dl.itc.u-tokyo.ac.jp/repo/iiif/167815/canvas/p20\", \"@id\": \"https://iiif.dl.itc.u-tokyo.ac.jp/repo/iiif/167815/annotation/p0020-image\"}], \"label\": \"[20]\"}, {\"@type\": \"sc:Canvas\", \"thumbnail\": {\"service\": {\"profile\": \"http://iiif.io/api/image/2/level2.json\", \"@context\": \"http://iiif.io/api/image/2/context.json\", \"@id\": \"https://iiif.dl.itc.u-tokyo.ac.jp/repo/iiif-img/168769\"}, \"@id\": \"https://iiif.dl.itc.u-tokyo.ac.jp/repo/iiif-img/168769/full/200,200/0/default.jpg\"}, \"width\": 7362, \"@id\": \"https://iiif.dl.itc.u-tokyo.ac.jp/repo/iiif/167815/canvas/p21\", \"height\": 6132, \"images\": [{\"motivation\": \"sc:painting\", \"@type\": \"oa:Annotation\", \"resource\": {\"@type\": \"dctypes:Image\", \"format\": \"image/jpeg\", \"width\": 7362, \"@id\": \"https://iiif.dl.itc.u-tokyo.ac.jp/repo/iiif-img/168769\", \"height\": 6132, \"service\": {\"profile\": \"http://iiif.io/api/image/2/level2.json\", \"tiles\": [{\"width\": 256, \"scaleFactors\": [1, 2, 4, 8, 16, 32]}], \"width\": 7362, \"@id\": \"https://iiif.dl.itc.u-tokyo.ac.jp/repo/iiif-img/168769\", \"@context\": \"http://iiif.io/api/image/2/context.json\", \"height\": 6132}}, \"on\": \"https://iiif.dl.itc.u-tokyo.ac.jp/repo/iiif/167815/canvas/p21\", \"@id\": \"https://iiif.dl.itc.u-tokyo.ac.jp/repo/iiif/167815/annotation/p0021-image\"}], \"label\": \"[21]\"}, {\"@type\": \"sc:Canvas\", \"thumbnail\": {\"service\": {\"profile\": \"http://iiif.io/api/image/2/level2.json\", \"@context\": \"http://iiif.io/api/image/2/context.json\", \"@id\": \"https://iiif.dl.itc.u-tokyo.ac.jp/repo/iiif-img/168770\"}, \"@id\": \"https://iiif.dl.itc.u-tokyo.ac.jp/repo/iiif-img/168770/full/200,200/0/default.jpg\"}, \"width\": 7362, \"@id\": \"https://iiif.dl.itc.u-tokyo.ac.jp/repo/iiif/167815/canvas/p22\", \"height\": 6132, \"images\": [{\"motivation\": \"sc:painting\", \"@type\": \"oa:Annotation\", \"resource\": {\"@type\": \"dctypes:Image\", \"format\": \"image/jpeg\", \"width\": 7362, \"@id\": \"https://iiif.dl.itc.u-tokyo.ac.jp/repo/iiif-img/168770\", \"height\": 6132, \"service\": {\"profile\": \"http://iiif.io/api/image/2/level2.json\", \"tiles\": [{\"width\": 256, \"scaleFactors\": [1, 2, 4, 8, 16, 32]}], \"width\": 7362, \"@id\": \"https://iiif.dl.itc.u-tokyo.ac.jp/repo/iiif-img/168770\", \"@context\": \"http://iiif.io/api/image/2/context.json\", \"height\": 6132}}, \"on\": \"https://iiif.dl.itc.u-tokyo.ac.jp/repo/iiif/167815/canvas/p22\", \"@id\": \"https://iiif.dl.itc.u-tokyo.ac.jp/repo/iiif/167815/annotation/p0022-image\"}], \"label\": \"[22]\"}, {\"@type\": \"sc:Canvas\", \"thumbnail\": {\"service\": {\"profile\": \"http://iiif.io/api/image/2/level2.json\", \"@context\": \"http://iiif.io/api/image/2/context.json\", \"@id\": \"https://iiif.dl.itc.u-tokyo.ac.jp/repo/iiif-img/168771\"}, \"@id\": \"https://iiif.dl.itc.u-tokyo.ac.jp/repo/iiif-img/168771/full/200,200/0/default.jpg\"}, \"width\": 7362, \"@id\": \"https://iiif.dl.itc.u-tokyo.ac.jp/repo/iiif/167815/canvas/p23\", \"height\": 6132, \"images\": [{\"motivation\": \"sc:painting\", \"@type\": \"oa:Annotation\", \"resource\": {\"@type\": \"dctypes:Image\", \"format\": \"image/jpeg\", \"width\": 7362, \"@id\": \"https://iiif.dl.itc.u-tokyo.ac.jp/repo/iiif-img/168771\", \"height\": 6132, \"service\": {\"profile\": \"http://iiif.io/api/image/2/level2.json\", \"tiles\": [{\"width\": 256, \"scaleFactors\": [1, 2, 4, 8, 16, 32]}], \"width\": 7362, \"@id\": \"https://iiif.dl.itc.u-tokyo.ac.jp/repo/iiif-img/168771\", \"@context\": \"http://iiif.io/api/image/2/context.json\", \"height\": 6132}}, \"on\": \"https://iiif.dl.itc.u-tokyo.ac.jp/repo/iiif/167815/canvas/p23\", \"@id\": \"https://iiif.dl.itc.u-tokyo.ac.jp/repo/iiif/167815/annotation/p0023-image\"}], \"label\": \"[23]\"}, {\"@type\": \"sc:Canvas\", \"thumbnail\": {\"service\": {\"profile\": \"http://iiif.io/api/image/2/level2.json\", \"@context\": \"http://iiif.io/api/image/2/context.json\", \"@id\": \"https://iiif.dl.itc.u-tokyo.ac.jp/repo/iiif-img/168772\"}, \"@id\": \"https://iiif.dl.itc.u-tokyo.ac.jp/repo/iiif-img/168772/full/200,200/0/default.jpg\"}, \"width\": 7362, \"@id\": \"https://iiif.dl.itc.u-tokyo.ac.jp/repo/iiif/167815/canvas/p24\", \"height\": 6132, \"images\": [{\"motivation\": \"sc:painting\", \"@type\": \"oa:Annotation\", \"resource\": {\"@type\": \"dctypes:Image\", \"format\": \"image/jpeg\", \"width\": 7362, \"@id\": \"https://iiif.dl.itc.u-tokyo.ac.jp/repo/iiif-img/168772\", \"height\": 6132, \"service\": {\"profile\": \"http://iiif.io/api/image/2/level2.json\", \"tiles\": [{\"width\": 256, \"scaleFactors\": [1, 2, 4, 8, 16, 32]}], \"width\": 7362, \"@id\": \"https://iiif.dl.itc.u-tokyo.ac.jp/repo/iiif-img/168772\", \"@context\": \"http://iiif.io/api/image/2/context.json\", \"height\": 6132}}, \"on\": \"https://iiif.dl.itc.u-tokyo.ac.jp/repo/iiif/167815/canvas/p24\", \"@id\": \"https://iiif.dl.itc.u-tokyo.ac.jp/repo/iiif/167815/annotation/p0024-image\"}], \"label\": \"[24]\"}, {\"@type\": \"sc:Canvas\", \"thumbnail\": {\"service\": {\"profile\": \"http://iiif.io/api/image/2/level2.json\", \"@context\": \"http://iiif.io/api/image/2/context.json\", \"@id\": \"https://iiif.dl.itc.u-tokyo.ac.jp/repo/iiif-img/168773\"}, \"@id\": \"https://iiif.dl.itc.u-tokyo.ac.jp/repo/iiif-img/168773/full/200,200/0/default.jpg\"}, \"width\": 7362, \"@id\": \"https://iiif.dl.itc.u-tokyo.ac.jp/repo/iiif/167815/canvas/p25\", \"height\": 6132, \"images\": [{\"motivation\": \"sc:painting\", \"@type\": \"oa:Annotation\", \"resource\": {\"@type\": \"dctypes:Image\", \"format\": \"image/jpeg\", \"width\": 7362, \"@id\": \"https://iiif.dl.itc.u-tokyo.ac.jp/repo/iiif-img/168773\", \"height\": 6132, \"service\": {\"profile\": \"http://iiif.io/api/image/2/level2.json\", \"tiles\": [{\"width\": 256, \"scaleFactors\": [1, 2, 4, 8, 16, 32]}], \"width\": 7362, \"@id\": \"https://iiif.dl.itc.u-tokyo.ac.jp/repo/iiif-img/168773\", \"@context\": \"http://iiif.io/api/image/2/context.json\", \"height\": 6132}}, \"on\": \"https://iiif.dl.itc.u-tokyo.ac.jp/repo/iiif/167815/canvas/p25\", \"@id\": \"https://iiif.dl.itc.u-tokyo.ac.jp/repo/iiif/167815/annotation/p0025-image\"}], \"label\": \"[25]\"}, {\"@type\": \"sc:Canvas\", \"thumbnail\": {\"service\": {\"profile\": \"http://iiif.io/api/image/2/level2.json\", \"@context\": \"http://iiif.io/api/image/2/context.json\", \"@id\": \"https://iiif.dl.itc.u-tokyo.ac.jp/repo/iiif-img/168774\"}, \"@id\": \"https://iiif.dl.itc.u-tokyo.ac.jp/repo/iiif-img/168774/full/200,200/0/default.jpg\"}, \"width\": 7362, \"@id\": \"https://iiif.dl.itc.u-tokyo.ac.jp/repo/iiif/167815/canvas/p26\", \"height\": 6132, \"images\": [{\"motivation\": \"sc:painting\", \"@type\": \"oa:Annotation\", \"resource\": {\"@type\": \"dctypes:Image\", \"format\": \"image/jpeg\", \"width\": 7362, \"@id\": \"https://iiif.dl.itc.u-tokyo.ac.jp/repo/iiif-img/168774\", \"height\": 6132, \"service\": {\"profile\": \"http://iiif.io/api/image/2/level2.json\", \"tiles\": [{\"width\": 256, \"scaleFactors\": [1, 2, 4, 8, 16, 32]}], \"width\": 7362, \"@id\": \"https://iiif.dl.itc.u-tokyo.ac.jp/repo/iiif-img/168774\", \"@context\": \"http://iiif.io/api/image/2/context.json\", \"height\": 6132}}, \"on\": \"https://iiif.dl.itc.u-tokyo.ac.jp/repo/iiif/167815/canvas/p26\", \"@id\": \"https://iiif.dl.itc.u-tokyo.ac.jp/repo/iiif/167815/annotation/p0026-image\"}], \"label\": \"[26]\"}, {\"@type\": \"sc:Canvas\", \"thumbnail\": {\"service\": {\"profile\": \"http://iiif.io/api/image/2/level2.json\", \"@context\": \"http://iiif.io/api/image/2/context.json\", \"@id\": \"https://iiif.dl.itc.u-tokyo.ac.jp/repo/iiif-img/168775\"}, \"@id\": \"https://iiif.dl.itc.u-tokyo.ac.jp/repo/iiif-img/168775/full/200,200/0/default.jpg\"}, \"width\": 7362, \"@id\": \"https://iiif.dl.itc.u-tokyo.ac.jp/repo/iiif/167815/canvas/p27\", \"height\": 6132, \"images\": [{\"motivation\": \"sc:painting\", \"@type\": \"oa:Annotation\", \"resource\": {\"@type\": \"dctypes:Image\", \"format\": \"image/jpeg\", \"width\": 7362, \"@id\": \"https://iiif.dl.itc.u-tokyo.ac.jp/repo/iiif-img/168775\", \"height\": 6132, \"service\": {\"profile\": \"http://iiif.io/api/image/2/level2.json\", \"tiles\": [{\"width\": 256, \"scaleFactors\": [1, 2, 4, 8, 16, 32]}], \"width\": 7362, \"@id\": \"https://iiif.dl.itc.u-tokyo.ac.jp/repo/iiif-img/168775\", \"@context\": \"http://iiif.io/api/image/2/context.json\", \"height\": 6132}}, \"on\": \"https://iiif.dl.itc.u-tokyo.ac.jp/repo/iiif/167815/canvas/p27\", \"@id\": \"https://iiif.dl.itc.u-tokyo.ac.jp/repo/iiif/167815/annotation/p0027-image\"}], \"label\": \"[27]\"}], \"@type\": \"sc:Sequence\", \"viewingHint\": \"non-paged\", \"label\": \"Current Page Order\", \"@id\": \"https://iiif.dl.itc.u-tokyo.ac.jp/repo/iiif/167815/sequence/normal\"}]}"
        },
        {
            "element": {
                "id": 63,
                "name": "UUID",
                "resource": "elements",
                "url": "https://diyhistory.org/uparl/omeka/api/elements/63"
            },
            "element_set": {
                "id": 6,
                "name": "IIIF Collection Metadata",
                "resource": "element_sets",
                "url": "https://diyhistory.org/uparl/omeka/api/element_sets/6"
            },
            "html": false,
            "text": "04ecae0b-57cc-4260-93bd-def339396440"
        }
    ],
    "extended_resources": [],
    "featured": false,
    "id": 41,
    "items": {
        "count": 27,
        "resource": "items",
        "url": "https://diyhistory.org/uparl/omeka/api/items?collection=41"
    },
    "modified": "2017-11-06T19:23:27+00:00",
    "owner": {
        "id": 1,
        "resource": "users",
        "url": "https://diyhistory.org/uparl/omeka/api/users/1"
    },
    "public": true,
    "url": "https://diyhistory.org/uparl/omeka/api/collections/41"
}