{
    "@context": "http://iiif.io/api/presentation/2/context.json",
    "@id": "https://raw.githubusercontent.com/nakamura196/omekac_uparl/master/docs/oa/items/1091/annolist.json",
    "@type": "sc:AnnotationList",
    "resources": [
        {
            "@context": "http://iiif.io/api/presentation/2/context.json",
            "@id": "https://diyhistory.org/uparl/omeka/oa/items/14799/anno.json",
            "@type": "oa:Annotation",
            "motivation": "oa:commenting",
            "on": [
                {
                    "@type": "oa:SpecificResource",
                    "full": "https://iiif.dl.itc.u-tokyo.ac.jp/repo/iiif/167816/canvas/p21",
                    "selector": {
                        "@type": "oa:Choice",
                        "default": {
                            "@type": "oa:FragmentSelector",
                            "value": "xywh=520,459,2544,5299"
                        },
                        "item": {
                            "@type": "oa:SvgSelector",
                            "value": "<svg xmlns='http://www.w3.org/2000/svg'><path xmlns=\"http://www.w3.org/2000/svg\" d=\"M3064.07822,5757.3574h-1271.88809v0h-1271.88809v-2649.31288v-2649.31288h1271.88809h1271.88809v2649.31288z\" data-paper-data=\"{&quot;strokeWidth&quot;:1,&quot;rotation&quot;:0,&quot;deleteIcon&quot;:null,&quot;rotationIcon&quot;:null,&quot;group&quot;:null,&quot;editable&quot;:true,&quot;annotation&quot;:null}\" id=\"rectangle_8f03192d-d5b6-4505-9422-5d7e1fed524a\" fill-opacity=\"0\" fill=\"#00bfff\" fill-rule=\"nonzero\" stroke=\"#00bfff\" stroke-width=\"1\" stroke-linecap=\"butt\" stroke-linejoin=\"miter\" stroke-miterlimit=\"10\" stroke-dasharray=\"\" stroke-dashoffset=\"0\" font-family=\"none\" font-weight=\"none\" font-size=\"none\" text-anchor=\"none\" style=\"mix-blend-mode: normal\"/></svg>"
                        }
                    },
                    "within": {
                        "@id": "https://raw.githubusercontent.com/nakamura196/omekac_uparl/master/docs/oa/items/1091/manifest.json",
                        "@type": "sc:Manifest"
                    }
                }
            ],
            "resource": [
                {
                    "@type": "dctypes:Text",
                    "chars": "<p><span style=\"font-size: 10pt; font-family: Arial;\" data-sheets-value=\"{&quot;1&quot;:2,&quot;2&quot;:&quot;戲鴻堂法書-16-26&quot;}\" data-sheets-userformat=\"{&quot;2&quot;:513,&quot;3&quot;:[null,0],&quot;12&quot;:0}\">戲鴻堂法書-16-26@東京大学</span></p>",
                    "format": "text/html"
                }
            ]
        }
    ]
}